hg_docgraph-0.0.4.dev0.dist-info/METADATA
hg_docgraph-0.0.4.dev0.dist-info/RECORD
hg_docgraph-0.0.4.dev0.dist-info/WHEEL
hg_docgraph-0.0.4.dev0.dist-info/top_level.txt
hgext3rd/__init__.py
hgext3rd/docgraph.py
